smitter/__init__.py
smitter/__version__.py
smitter-0.0.1.dist-info/LICENSE
smitter-0.0.1.dist-info/METADATA
smitter-0.0.1.dist-info/WHEEL
smitter-0.0.1.dist-info/top_level.txt
smitter-0.0.1.dist-info/RECORD
